__init__.py
pypfc.py
pypfc_base.py
pypfc_grid.py
pypfc_io.py
pypfc_ovito.py
pypfc_pre.py
pypfc-0.0.4.dist-info/licenses/LICENSE
pypfc-0.0.4.dist-info/METADATA
pypfc-0.0.4.dist-info/WHEEL
pypfc-0.0.4.dist-info/top_level.txt
pypfc-0.0.4.dist-info/RECORD
