Metadata-Version: 2.4
Name: pypfc
Version: 0.0.4
Summary: A Python Package for Phase Field Crystal (PFC) Simulations
Author-email: Håkan Hallberg <hakan.hallb@protonmail.com>
License-Expression: GPL-3.0-or-later
Project-URL: Homepage, https://github.com/HHallb/pyPFC
Project-URL: Repository, https://github.com/HHallb/pyPFC
Keywords: phase field crystal,simulation,atomistic simulation,gpu
Classifier: Programming Language :: Python :: 3
Classifier: Programming Language :: Python :: 3.11
Classifier: Programming Language :: Python :: 3.12
Classifier: Programming Language :: Python :: 3.13
Classifier: Operating System :: OS Independent
Classifier: Development Status :: 4 - Beta
Requires-Python: <3.14,>=3.11
License-File: LICENSE
Requires-Dist: numpy
Requires-Dist: scipy
Requires-Dist: vtk
Requires-Dist: torch
Requires-Dist: scikit-image
Dynamic: license-file
